.gitignore
README.md
pyproject.toml
service/__init__.py
service/__main__.py
service/_commands.py
service/_configure.py
service/_uvicorn.py
service/ext/__init__.py
service/ext/api_type.py
service/ext/const.py
service/ext/crypt.py
service/ext/endpoint.py
service/ext/enum.py
service/ext/exc.py
service/ext/fn.py
service/ext/middleware.py
service/ext/params.py
service/ext/roles.py
service/ext/testing.py
service/log/__init__.py
service/log/formatter.py
service/log/style.py
dep_service-2.12.0.dist-info/WHEEL
dep_service-2.12.0.dist-info/METADATA
dep_service-2.12.0.dist-info/RECORD
