Metadata-Version: 2.1
Name: dep-service
Version: 2.12.0
Summary: 
Author: everhide
Author-email: i.tolkachnikov@gmail.com
Requires-Python: >=3.9,<=3.11
Classifier: Programming Language :: Python :: 3
Classifier: Programming Language :: Python :: 3.10
Classifier: Programming Language :: Python :: 3.9
Requires-Dist: APScheduler (>=3.9.1,<4.0.0)
Requires-Dist: PyJWT (>=2.6.0,<3.0.0)
Requires-Dist: PyYAML (>=6.0,<7.0)
Requires-Dist: Pygments (>=2.12.0,<3.0.0)
Requires-Dist: asgi-lifespan (>=1.0.1,<2.0.0)
Requires-Dist: cryptography (>=39.0.0,<40.0.0)
Requires-Dist: ddtrace (>=1.6.3,<2.0.0)
Requires-Dist: dep-spec (==2.3.29)
Requires-Dist: fastapi-utils (>=0.2.1,<0.3.0)
Requires-Dist: fire (>=0.4.0,<0.5.0)
Requires-Dist: flake8 (==3.9.0)
Requires-Dist: flake8-bandit (>=3.0.0,<4.0.0)
Requires-Dist: flake8-docstrings (>=1.6.0,<2.0.0)
Requires-Dist: flakehell (>=0.9.0,<0.10.0)
Requires-Dist: httpx (>=0.23.0,<0.24.0)
Requires-Dist: logging-json (>=0.2.1,<0.3.0)
Requires-Dist: orjson (>=3.8.1,<4.0.0)
Requires-Dist: pytest (>=7.1.2,<8.0.0)
Requires-Dist: pytest-asyncio (>=0.19.0,<0.20.0)
Requires-Dist: pytest-httpx (>=0.21.0,<0.22.0)
Requires-Dist: python-i18n (>=0.3.9,<0.4.0)
Requires-Dist: requests (>=2.28.1,<3.0.0)
Requires-Dist: respx (>=0.20.1,<0.21.0)
Requires-Dist: sentry-sdk (>=1.9.5,<2.0.0)
Requires-Dist: ujson (>=5.5.0,<6.0.0)
